extrema.py
extrema-1.0.0.dist-info/LICENSE
extrema-1.0.0.dist-info/METADATA
extrema-1.0.0.dist-info/WHEEL
extrema-1.0.0.dist-info/top_level.txt
extrema-1.0.0.dist-info/RECORD
