Metadata-Version: 2.2
Name: extrema
Version: 1.0.0
Summary: Finding an iterable's minima or maxima.
Author-email: John Dawson <john.a.dawson@proton.me>
Maintainer-email: John Dawson <john.a.dawson@proton.me>
License:                     GNU GENERAL PUBLIC LICENSE
Project-URL: Homepage, https://github.com/JohnADawson/extrema
Project-URL: Documentation, https://github.com/JohnADawson/extrema/blob/master/src/extrema.py
Keywords: max,maxima,maximize,min,minima,minimize
License-File: LICENSE
